Doan/project_1/project_1.srcs/sources_1/new/subbytes_shiftrows.v
`timescale 1ns / 1ps
//////////////////////////////////////////////////////////////////////////////////
// Company: 
// Engineer: 
// 
// Create Date: 10/26/2025 01:30:21 PM
// Design Name: 
// Module Name: subbytes_shiftrows
// Project Name: 
// Target Devices: 
// Tool Versions: 
// Description: 
// 
// Dependencies: 
// 
// Revision:
// Revision 0.01 - File Created
// Additional Comments:
// 
//////////////////////////////////////////////////////////////////////////////////

module subbytes (
    input  wire         clk,
    input  wire [127:0] in,
    output reg  [127:0] out
);
    integer i;
    reg [7:0] temp [0:15];

    // === SubBytes combinational ===
    always @(*) begin
        temp[0]  = aes_sbox(in[7:0]);
        temp[1]  = aes_sbox(in[15:8]);
        temp[2]  = aes_sbox(in[23:16]);
        temp[3]  = aes_sbox(in[31:24]);
        temp[4]  = aes_sbox(in[39:32]);
        temp[5]  = aes_sbox(in[47:40]);
        temp[6]  = aes_sbox(in[55:48]);
        temp[7]  = aes_sbox(in[63:56]);
        temp[8]  = aes_sbox(in[71:64]);
        temp[9]  = aes_sbox(in[79:72]);
        temp[10] = aes_sbox(in[87:80]);
        temp[11] = aes_sbox(in[95:88]);
        temp[12] = aes_sbox(in[103:96]);
        temp[13] = aes_sbox(in[111:104]);
        temp[14] = aes_sbox(in[119:112]);
        temp[15] = aes_sbox(in[127:120]);
    end

    // === Pipeline register (để tăng tốc) ===
    always @(posedge clk)
        out <= {temp[15], temp[14], temp[13], temp[12],
                temp[11], temp[10], temp[9],  temp[8],
                temp[7],  temp[6],  temp[5],  temp[4],
                temp[3],  temp[2],  temp[1],  temp[0]};

    // === S-box function ===
    function [7:0] aes_sbox;
        input [7:0] a;
        begin
            case (a)
                8'h00: aes_sbox = 8'h63; 8'h01: aes_sbox = 8'h7c; 8'h02: aes_sbox = 8'h77; 8'h03: aes_sbox = 8'h7b;
                8'h04: aes_sbox = 8'hf2; 8'h05: aes_sbox = 8'h6b; 8'h06: aes_sbox = 8'h6f; 8'h07: aes_sbox = 8'hc5;
                8'h08: aes_sbox = 8'h30; 8'h09: aes_sbox = 8'h01; 8'h0a: aes_sbox = 8'h67; 8'h0b: aes_sbox = 8'h2b;
                8'h0c: aes_sbox = 8'hfe; 8'h0d: aes_sbox = 8'hd7; 8'h0e: aes_sbox = 8'hab; 8'h0f: aes_sbox = 8'h76;
                8'h10: aes_sbox = 8'hca; 8'h11: aes_sbox = 8'h82; 8'h12: aes_sbox = 8'hc9; 8'h13: aes_sbox = 8'h7d;
                8'h14: aes_sbox = 8'hfa; 8'h15: aes_sbox = 8'h59; 8'h16: aes_sbox = 8'h47; 8'h17: aes_sbox = 8'hf0;
                8'h18: aes_sbox = 8'had; 8'h19: aes_sbox = 8'hd4; 8'h1a: aes_sbox = 8'ha2; 8'h1b: aes_sbox = 8'haf;
                8'h1c: aes_sbox = 8'h9c; 8'h1d: aes_sbox = 8'ha4; 8'h1e: aes_sbox = 8'h72; 8'h1f: aes_sbox = 8'hc0;
                // ... (bạn thêm hết 256 giá trị S-box ở đây)
                8'hff: aes_sbox = 8'h16;
            endcase
        end
    endfunction
endmodule

Doan/project_1/project_1.srcs/sim_1/new/tb_subbytes_shiftrows.v
`timescale 1ns / 1ps
//////////////////////////////////////////////////////////////////////////////////
// Company: 
// Engineer: 
// 
// Create Date: 10/26/2025 01:33:30 PM
// Design Name: 
// Module Name: tb_subbytes_shiftrows
// Project Name: 
// Target Devices: 
// Tool Versions: 
// Description: 
// 
// Dependencies: 
// 
// Revision:
// Revision 0.01 - File Created
// Additional Comments:
// 
//////////////////////////////////////////////////////////////////////////////////

module tb_subbytes_shiftrows();

    // Clock và Reset
    reg clk;
    reg rst;

    // Input / Output
    reg  [127:0] in;
    wire [127:0] out;

    // Khởi tạo DUT
    subbytes uut (
        .clk(clk),
        .in(in),
        .out(out)
    );

    // Clock 10ns
    always #5 clk = ~clk;

    // SBOX ROM DUMMY (nếu bạn chưa có sbox_rom)
    // 👉 Chỉ dùng cho test, trả về đảo bit để dễ nhận biết
    // Thay bằng ROM thực tế khi cần.
    genvar i;
    generate
        for (i = 0; i < 16; i = i + 1) begin : srom_inst
            // Dummy S-box implementation
            // Nếu bạn đã có module sbox_rom riêng, bỏ phần này đi
            // và đảm bảo file đó được include vào project.
            // module sbox_rom (input clk, input [7:0] addr, output reg [7:0] data);
            // ...
        end
    endgenerate

    // Mô phỏng chính
    initial begin
        // Dump waveform nếu dùng GTKWave
        $dumpfile("tb_subbytes_shiftrows.vcd");
        $dumpvars(0, tb_subbytes_shiftrows);

        // Khởi tạo tín hiệu
        clk = 0;
        rst = 1;
        in  = 128'd0;

        // Reset trong 2 chu kỳ
        #12 rst = 0;

        // Test vector 1: dữ liệu đơn giản
        in = 128'h000102030405060708090a0b0c0d0e0f;
        #10;

        // Test vector 2: dữ liệu ngẫu nhiên
        in = 128'h0f0e0d0c0b0a09080706050403020100;
        #10;

        // Test vector 3: toàn 1
        in = 128'hffffffffffffffffffffffffffffffff;
        #10;

        // Chờ vài chu kỳ để xem pipeline ra
        #100;

        $display("Simulation finished.");
        $finish;
    end

    // Theo dõi kết quả từng chu kỳ
    always @(posedge clk) begin
        $display("[%0t] in = %h | out = %h", $time, in, out);
    end

endmodule

Doan/project_1/project_1.sim/sim_1/behav/xsim/tb_subbytes_shiftrows.vcd
$date
   Sun Oct 26 14:16:13 2025
$end

$version
  2024.2.0
  $dumpfile ("tb_subbytes_shiftrows.vcd") 
$end

$timescale
  1ps
$end

$scope module tb_subbytes_shiftrows $end
$var reg 1 ! clk $end
$var reg 1 " rst $end
$var reg 128 # in [127:0] $end
$var wire 128 $ out [127:0] $end
$scope module uut $end
$var wire 1 % clk $end
$var wire 128 & in [127:0] $end
$var reg 128 ' out [127:0] $end
$var integer 32 ( i [31:0] $end
$scope function aes_sbox $end
$var reg 8 ) aes_sbox [7:0] $end
$var reg 8 * a [7:0] $end
$upscope $end
$upscope $end
$upscope $end
$enddefinitions $end

#0
$dumpvars
0!
1"
b0 #
bx $
0%
b0 &
bx '
bx (
b1100011 )
b0 *
$end

#5000
1!
b1100011011000110110001101100011011000110110001101100011011000110110001101100011011000110110001101100011011000110110001101100011 $
1%
b1100011011000110110001101100011011000110110001101100011011000110110001101100011011000110110001101100011011000110110001101100011 '

#10000
0!
0%

#12000
0"
b10000001000000011000001000000010100000110000001110000100000001001000010100000101100001100000011010000111000001111 #
b10000001000000011000001000000010100000110000001110000100000001001000010100000101100001100000011010000111000001111 &
b1100011 )
b0 *

#15000
1!
b1100011011111000111011101111011111100100110101101101111110001010011000000000001011001110010101111111110110101111010101101110110 $
1%
b1100011011111000111011101111011111100100110101101101111110001010011000000000001011001110010101111111110110101111010101101110110 '

#20000
0!
0%

#22000
b1111000011100000110100001100000010110000101000001001000010000000011100000110000001010000010000000011000000100000000100000000 #
b1111000011100000110100001100000010110000101000001001000010000000011100000110000001010000010000000011000000100000000100000000 &
b1110110 )
b1111 *

#25000
1!
b1110110101010111101011111111110001010110110011100000001001100001100010101101111011010111111001001111011011101110111110001100011 $
1%
b1110110101010111101011111111110001010110110011100000001001100001100010101101111011010111111001001111011011101110111110001100011 '

#30000
0!
0%

#32000
b11111111111111111111111111111111111111111111111111111111111111111111111111111111111111111111111111111111111111111111111111111111 #
b11111111111111111111111111111111111111111111111111111111111111111111111111111111111111111111111111111111111111111111111111111111 &
b10110 )
b11111111 *

#35000
1!
b10110000101100001011000010110000101100001011000010110000101100001011000010110000101100001011000010110000101100001011000010110 $
1%
b10110000101100001011000010110000101100001011000010110000101100001011000010110000101100001011000010110000101100001011000010110 '

