verilog/FP_adder.v
module FP_adder#(
	parameter PRECISION = 32,
	parameter EXPONENT  = 8,
	parameter FRACTION  = 23,
	parameter BIAS 	    = 127
)(
	input clk,
	input reset_n,
	input   [PRECISION-1:0] a_operand, 		//format of IEEE-754 standard
	input   [PRECISION-1:0] b_operand, 		//format of IEEE-754 standard
	output reg [PRECISION-1:0] result 		//format of IEEE-754 standard 
);

//---------------------------- EXTRACT ----------------------------//
wire sign_a;
wire [EXPONENT-1:0] expo_a;
wire [FRACTION-1:0] frac_a;
assign sign_a = a_operand[PRECISION-1];
assign expo_a = a_operand[PRECISION-2 -: EXPONENT];
assign frac_a = a_operand[FRACTION-1:0]; 

wire sign_b;
wire [EXPONENT-1:0] expo_b;
wire [FRACTION-1:0] frac_b;
assign sign_b = b_operand[PRECISION-1];
assign expo_b = b_operand[PRECISION-2 -: EXPONENT];
assign frac_b = b_operand[FRACTION-1:0];
//---------------------------- EXTRACT ----------------------------//

// Stage 1: align
wire signed [EXPONENT:0] expo_unbiased_a;
wire signed [EXPONENT:0] expo_unbiased_b;
wire [FRACTION:0] mant_a;
wire [FRACTION:0] mant_b;

assign expo_unbiased_a =  $signed({1'b0, expo_a}) - $signed(BIAS);
assign expo_unbiased_b =  $signed({1'b0, expo_b}) - $signed(BIAS);
assign mant_a = {1'b1, frac_a};
assign mant_b = {1'b1, frac_b};
///////////
wire a_gt_b;
assign a_gt_b = (expo_unbiased_a > expo_unbiased_b) ? 1 : 0;

wire [EXPONENT:0] expo_diff;
wire signed [EXPONENT:0] expo_larger, expo_norm, expo_shift;
wire [FRACTION:0] mant_norm_t, mant_shift_t, mant_norm, mant_shift;
wire sign_norm, sign_shift;
wire sign_res;

assign expo_diff 	= (a_gt_b) ? expo_unbiased_a - expo_unbiased_b : expo_unbiased_b - expo_unbiased_a; 	
assign expo_larger 	= (a_gt_b) ? expo_unbiased_a : expo_unbiased_b; 					

assign mant_norm_t 	= (a_gt_b) ? mant_a : mant_b; 
assign mant_shift_t 	= (a_gt_b) ? mant_b >> expo_diff : mant_a >> expo_diff;

assign sign_norm 	= (a_gt_b) ? sign_a : sign_b;
assign sign_shift 	= (a_gt_b) ? sign_b : sign_a;

assign mant_norm 	= (sign_norm)  ? (~mant_norm_t  + 1'b1) : mant_norm_t;
assign mant_shift 	= (sign_shift) ? (~mant_shift_t + 1'b1) : mant_shift_t;
assign sign_res 	= (sign_norm  && sign_shift ||
			   sign_norm  && mant_norm_t > mant_shift_t || 
			   sign_shift && mant_shift_t > mant_norm_t) ? 1 : 0; 

reg [2 + 1 + EXPONENT + 1 + (FRACTION + 1)*2 - 1 : 0] align;
always @(posedge clk or negedge reset_n) begin
	if(!reset_n) begin
		align <= 0;
	end else begin
		//align <= { sign_res, expo_larger, (sign_norm)  ? (~mant_norm  + 1'b1) : mant_norm, (sign_shift) ? (~mant_shift + 1'b1) : mant_shift };
		align <= { sign_norm, sign_shift, sign_res, expo_larger, mant_norm, mant_shift };
	end
end

// Stage 2: add/sub mantissa
wire sign_s1, sign_norm_s1, sign_shift_s1;
wire signed [EXPONENT:0] expo_s1;
wire [FRACTION:0] mant_norm_s1, mant_shift_s1;
wire [FRACTION+1:0] mant_sum; //including carry bit  

assign {sign_norm_s1, sign_shift_s1, sign_s1, expo_s1, mant_norm_s1, mant_shift_s1} = align;
assign mant_sum = mant_norm_s1 + mant_shift_s1;  

reg [2 + 1 + (EXPONENT+1) + (FRACTION+1+1) - 1 : 0] add_significands;
always @(posedge clk or negedge reset_n) begin
    	if (!reset_n)
        	add_significands <= 0;
    	else 
        	add_significands <= {sign_norm_s1, sign_shift_s1, sign_s1, expo_s1, (sign_s1) ? ~mant_sum + 1'b1 : mant_sum};

end

// Stage 3: normalize
wire sign_s2, sign_norm_s2, sign_shift_s2;
wire signed [EXPONENT:0] expo_s2;
wire [FRACTION+1:0] mant_sum_s2;
assign {sign_norm_s2, sign_shift_s2, sign_s2, expo_s2, mant_sum_s2} = add_significands;

reg signed [EXPONENT:0] expo_s2_r;
reg [FRACTION+1:0] mant_sum_s2_r;

reg [1 + (EXPONENT+1) + (FRACTION+1+1) - 1 : 0] normalize;
integer i;
always @(posedge clk or negedge reset_n) begin
    	if (!reset_n) begin
        	normalize <= 0;
    	end else begin
        	mant_sum_s2_r 	= mant_sum_s2;
        	expo_s2_r 	= expo_s2;

		if (mant_sum_s2[FRACTION+1] && sign_norm_s2 == sign_shift_s2) begin  	//OVERFLOW
			mant_sum_s2_r = mant_sum_s2_r >> 1;
			expo_s2_r = expo_s2_r + 1;
		end 

		for (i = 0; i < FRACTION+1; i = i + 1) begin 				//UNDERFLOW
			if (mant_sum_s2_r[FRACTION] == 0 && mant_sum_s2_r != 0) begin
				mant_sum_s2_r = mant_sum_s2_r << 1;
				expo_s2_r = expo_s2_r - 1;
			end
		end
		
        	normalize = {sign_s2, expo_s2_r, mant_sum_s2_r};
    	end
end

// Stage 5: rounding 
wire sign_s3;
wire signed [EXPONENT:0] expo_s3;
wire [FRACTION+1:0] mant_sum_s3;

assign {sign_s3, expo_s3, mant_sum_s3} = normalize;

wire [EXPONENT-1:0] expo_rounded;
wire [FRACTION-1:0] mant_rounded;
assign mant_rounded = mant_sum_s3[FRACTION-1:0]; 
assign expo_rounded = expo_s3[EXPONENT-1:0] + BIAS;

always @(posedge clk or negedge reset_n) begin
    	if (!reset_n) begin
        	result <= 0;
    	end else begin
        	result <= {sign_s3, expo_rounded, mant_rounded};
    	end
end

endmodule

verilog/FP_adder_tb.v
`timescale 1ns/1ps

module FP_adder_tb;

// Parameter match module under test
parameter PRECISION = 32;
parameter EXPONENT  = 8;
parameter FRACTION  = 23;

// DUT I/O
reg clk;
reg reset_n;
reg signed [PRECISION-1:0] a_operand;
reg signed [PRECISION-1:0] b_operand;
wire signed [PRECISION-1:0] result;

// Instantiate DUT
FP_adder #(
    .PRECISION(PRECISION),
    .EXPONENT(EXPONENT),
    .FRACTION(FRACTION)
) uut (
    .clk(clk),
    .reset_n(reset_n),
    .a_operand(a_operand),
    .b_operand(b_operand),
    .result(result)
);

// Clock generation
initial begin
    clk = 0;
    forever #5 clk = ~clk; // 100MHz clock
end

// Stimulus
initial begin
    // Initialize
    reset_n = 0;
    a_operand = 0;
    b_operand = 0;

    #15;
    reset_n = 1;

    /*
    //0.5 + (-0.4375)
    a_operand = 32'h3f000000; 
    b_operand = 32'hbee00000;
    #50;
    $display("0.5 + (-0.4375) = %h", result);

    // -2.5 + -1.5
    a_operand = 32'hC0200000; // -2.5
    b_operand = 32'hBFC00000; // -1.5
    #60;
    $display("-2.5 + -1.5 = %h", result);

    // 3.25 + (-1.5)
    a_operand = 32'h40500000; // 3.25
    b_operand = 32'hBFC00000; // -1.5
    #60;
    $display("3.25 + (-1.5) = %h", result);

    // 10.0 + 0.5
    a_operand = 32'h41200000; // 10.0
    b_operand = 32'h3F000000; // 0.5
    #60;
    $display("10.0 + 0.5 = %h", result);
    */

    // 1.0 + (-0.875)
    a_operand = 32'h3F800000; // 1.0
    b_operand = 32'hBEE00000; // -0.4375
    #10;

    // -2.5 + -1.5
    a_operand = 32'hC0200000; // -2.5
    b_operand = 32'hBFC00000; // -1.5
    #10;

    // 3.25 + (-1.5)
    a_operand = 32'h40500000; // 3.25
    b_operand = 32'hBFC00000; // -1.5
    #10;

    // 10.0 + 0.5
    a_operand = 32'h41200000; // 10.0
    b_operand = 32'h3F000000; // 0.5
    #10;

    // ---- Nhóm 1: số dương nhỏ ----
    a_operand = 32'h3E800000; // 0.25
    b_operand = 32'h3E000000; // 0.125
    #10;

    a_operand = 32'h3F000000; // 0.5
    b_operand = 32'h3E800000; // 0.25
    #10;

    a_operand = 32'h3F800000; // 1.0
    b_operand = 32'h3F000000; // 0.5
    #10;

    a_operand = 32'h3FA00000; // 1.25
    b_operand = 32'h3F400000; // 0.75
    #10;

    a_operand = 32'h3FC00000; // 1.5
    b_operand = 32'h3FC00000; // 1.5
    #10;

    a_operand = 32'h3FE00000; // 1.75
    b_operand = 32'h3F800000; // 1.0
    #10;

    // ---- Nhóm 2: số âm nhỏ ----
    a_operand = 32'hBE800000; // -0.25
    b_operand = 32'hBE000000; // -0.125
    #10;

    a_operand = 32'hBF000000; // -0.5
    b_operand = 32'hBE800000; // -0.25
    #10;

    a_operand = 32'hBF800000; // -1.0
    b_operand = 32'hBF000000; // -0.5
    #10;

    a_operand = 32'hBFA00000; // -1.25
    b_operand = 32'hBF400000; // -0.75
    #10;

    a_operand = 32'hBFC00000; // -1.5
    b_operand = 32'hBFC00000; // -1.5
    #10;

    a_operand = 32'hBFE00000; // -1.75
    b_operand = 32'hBF800000; // -1.0
    #10;

    // ---- Nhóm 3: dương + âm ----
    a_operand = 32'h40000000; // 2.0
    b_operand = 32'hBF000000; // -0.5
    #10;

    a_operand = 32'h40400000; // 3.0
    b_operand = 32'hBF800000; // -1.0
    #10;

    a_operand = 32'h40A00000; // 5.0
    b_operand = 32'hC0000000; // -2.0
    #10;

    a_operand = 32'h40C00000; // 6.0
    b_operand = 32'hC0800000; // -4.0
    #10;

    a_operand = 32'h41200000; // 10.0
    b_operand = 32'hC0A00000; // -5.0
    #10;

    // ---- Nhóm 4: âm + dương ----
    a_operand = 32'hC0A00000; // -5.0
    b_operand = 32'h40A00000; // 5.0
    #10;

    a_operand = 32'hC1000000; // -8.0
    b_operand = 32'h41000000; // 8.0
    #10;

    a_operand = 32'hC0E00000; // -7.0
    b_operand = 32'h40A00000; // 5.0
    #10;

    a_operand = 32'hC1200000; // -10.0
    b_operand = 32'h40A00000; // 5.0
    #10;

    a_operand = 32'hC1A00000; // -20.0
    b_operand = 32'h41200000; // 10.0
    #10;

    // ---- Nhóm 5: số lớn ----
    a_operand = 32'h42C80000; // 100.0
    b_operand = 32'h41200000; // 10.0
    #10;

    a_operand = 32'h447A0000; // 1000.0
    b_operand = 32'h42C80000; // 100.0
    #10;

    a_operand = 32'h461C4000; // 10000.0
    b_operand = 32'h447A0000; // 1000.0
    #10;

    a_operand = 32'h49742400; // 1000000.0
    b_operand = 32'h42C80000; // 100.0
    #10;

    a_operand = 32'h4F800000; // 4.2949673e9 (gần max)
    b_operand = 32'h3F800000; // 1.0
    #10;

    // ---- Nhóm 6: số rất nhỏ (denormalized range) ----
    a_operand = 32'h00000001; // gần 0+
    b_operand = 32'h00000002; // gần 0+
    #10;

    a_operand = 32'h00800000; // 1.17549435e-38
    b_operand = 32'h00000001; // rất nhỏ
    #10;

    a_operand = 32'h3EAAAAAB; // 0.3333333
    b_operand = 32'h3E4CCCCD; // 0.2
    #10;

    // ---- Nhóm 7: số có phần thập phân lạ ----
    a_operand = 32'h3F99999A; // 1.2
    b_operand = 32'h3FCCCCCD; // 1.6
    #10;

    a_operand = 32'h40266666; // 2.6
    b_operand = 32'h3F99999A; // 1.2
    #10;

    a_operand = 32'h40A66666; // 5.2
    b_operand = 32'hC0A00000; // -5.0

    #50;
    $finish;
end

initial begin
    $dumpfile("FP_adder_tb.vcd");
    $dumpvars(0, FP_adder_tb);

    $monitor("opA = %h | opB = %h | result = %h", a_operand, b_operand, result);
end

endmodule

verilog/FP_adder_tb.vcd
$date
	Fri Oct 17 13:27:10 2025
$end
$version
	Icarus Verilog
$end
$timescale
	1ps
$end
$scope module FP_adder_tb $end
$var wire 32 ! result [31:0] $end
$var parameter 32 " EXPONENT $end
$var parameter 32 # FRACTION $end
$var parameter 32 $ PRECISION $end
$var reg 32 % a_operand [31:0] $end
$var reg 32 & b_operand [31:0] $end
$var reg 1 ' clk $end
$var reg 1 ( reset_n $end
$scope module uut $end
$var wire 32 ) a_operand [31:0] $end
$var wire 32 * b_operand [31:0] $end
$var wire 1 ' clk $end
$var wire 1 ( reset_n $end
$var wire 1 + sign_shift_s2 $end
$var wire 1 , sign_shift_s1 $end
$var wire 1 - sign_shift $end
$var wire 1 . sign_s3 $end
$var wire 1 / sign_s2 $end
$var wire 1 0 sign_s1 $end
$var wire 1 1 sign_res $end
$var wire 1 2 sign_norm_s2 $end
$var wire 1 3 sign_norm_s1 $end
$var wire 1 4 sign_norm $end
$var wire 1 5 sign_b $end
$var wire 1 6 sign_a $end
$var wire 25 7 mant_sum_s3 [24:0] $end
$var wire 25 8 mant_sum_s2 [24:0] $end
$var wire 25 9 mant_sum [24:0] $end
$var wire 24 : mant_shift_t [23:0] $end
$var wire 24 ; mant_shift_s1 [23:0] $end
$var wire 24 < mant_shift [23:0] $end
$var wire 23 = mant_rounded [22:0] $end
$var wire 24 > mant_norm_t [23:0] $end
$var wire 24 ? mant_norm_s1 [23:0] $end
$var wire 24 @ mant_norm [23:0] $end
$var wire 24 A mant_b [23:0] $end
$var wire 24 B mant_a [23:0] $end
$var wire 23 C frac_b [22:0] $end
$var wire 23 D frac_a [22:0] $end
$var wire 9 E expo_unbiased_b [8:0] $end
$var wire 9 F expo_unbiased_a [8:0] $end
$var wire 9 G expo_s3 [8:0] $end
$var wire 9 H expo_s2 [8:0] $end
$var wire 9 I expo_s1 [8:0] $end
$var wire 8 J expo_rounded [7:0] $end
$var wire 9 K expo_larger [8:0] $end
$var wire 9 L expo_diff [8:0] $end
$var wire 8 M expo_b [7:0] $end
$var wire 8 N expo_a [7:0] $end
$var wire 1 O a_gt_b $end
$var parameter 32 P BIAS $end
$var parameter 32 Q EXPONENT $end
$var parameter 32 R FRACTION $end
$var parameter 32 S PRECISION $end
$var reg 37 T add_significands [36:0] $end
$var reg 60 U align [59:0] $end
$var reg 9 V expo_s2_r [8:0] $end
$var reg 25 W mant_sum_s2_r [24:0] $end
$var reg 35 X normalize [34:0] $end
$var reg 32 Y result [31:0] $end
$var integer 32 Z i [31:0] $end
$upscope $end
$upscope $end
$enddefinitions $end
$comment Show the parameter values. $end
$dumpall
b100000 S
b10111 R
b1000 Q
b1111111 P
b100000 $
b10111 #
b1000 "
$end
#0
$dumpvars
bx Z
b0 Y
b0 X
bx W
bx V
b0 U
b0 T
0O
b0 N
b0 M
b0 L
b110000001 K
b1111111 J
b0 I
b0 H
b0 G
b110000001 F
b110000001 E
b0 D
b0 C
b100000000000000000000000 B
b100000000000000000000000 A
b100000000000000000000000 @
b0 ?
b100000000000000000000000 >
b0 =
b100000000000000000000000 <
b0 ;
b100000000000000000000000 :
b0 9
b0 8
b0 7
06
05
04
03
02
01
00
0/
0.
0-
0,
0+
b0 *
b0 )
0(
0'
b0 &
b0 %
b0 !
$end
#5000
1'
#10000
0'
#15000
b110000001 I
b100000000000000000000000 ?
b1000000000000000000000000 9
b100000000000000000000000 ;
b110000001100000000000000000000000100000000000000000000000 U
b111111100000000000000000000000 !
b111111100000000000000000000000 Y
01
1-
b110010000000000000000000 <
1O
b1110000000000000000000 :
b0 K
b100000000000000000000000 @
b10 L
04
b111111110 E
b100000000000000000000000 >
b0 F
b11000 Z
b0 V
b0 W
15
b1111101 M
b111000000000000000000000 A
b11000000000000000000000 C
b1111111 N
1'
b10111110111000000000000000000000 &
b10111110111000000000000000000000 *
b111111100000000000000000000000 %
b111111100000000000000000000000 )
1(
#20000
0'
#25000
b110000001 H
b1000000000000000000000000 8
1,
b0 I
b1010010000000000000000000 9
b110010000000000000000000 ;
b1100000011000000000000000000000000 T
b10000000000100000000000000000000000110010000000000000000000 U
11
b101000000000000000000000 <
b1 L
b1 K
b11000000000000000000000 @
b0 E
b11000000000000000000000 :
14
b1 F
b101000000000000000000000 >
b11000 Z
b1111111 M
b110000000000000000000000 A
b10000000000000000000000 C
16
b10000000 N
b101000000000000000000000 B
b1000000000000000000000 D
1'
b10111111110000000000000000000000 &
b10111111110000000000000000000000 *
b11000000001000000000000000000000 %
b11000000001000000000000000000000 )
#30000
0'
#35000
13
10
b1 I
b11000000000000000000000 ?
b1000000000000000000000000 9
b101000000000000000000000 ;
1+
b0 H
b1010010000000000000000000 8
b111000000001011000000000000000000000101000000000000000000000 U
b100000000001010010000000000000000000 T
01
b1 J
b110100000000000000000000 @
b110000010 G
b100000000000000000000000 7
04
b110100000000000000000000 >
b1100000100100000000000000000000000 X
b11000 Z
b110000010 V
b100000000000000000000000 W
06
b110100000000000000000000 B
b10100000000000000000000 D
1'
b1000000010100000000000000000000 %
b1000000010100000000000000000000 )
#40000
0'
#45000
12
1/
b1 H
b1000000000000000000000000 8
03
00
b1011100000000000000000000 9
b110100000000000000000000 ?
b100000000000000000000000 !
b100000000000000000000000 Y
b1110000000011000000000000000000000000 T
b10000000001110100000000000000000000101000000000000000000000 U
b1111110 J
b100000000000000000000 =
b10000000000000000000 <
b100 L
b11 K
b101000000000000000000000 @
b111111111 G
b100100000000000000000000 7
0-
b111111111 E
b10000000000000000000 :
b11 F
b101000000000000000000000 >
b1111111110100100000000000000000000 X
b11000 Z
b111111111 V
b100100000000000000000000 W
05
b1111110 M
b100000000000000000000000 A
b0 C
b10000010 N
b101000000000000000000000 B
b1000000000000000000000 D
1'
b111111000000000000000000000000 &
b111111000000000000000000000000 *
b1000001001000000000000000000000 %
b1000001001000000000000000000000 )
#50000
0'
#55000
0,
b11 I
b101000000000000000000000 ?
b101010000000000000000000 9
b10000000000000000000 ;
02
0/
b1011100000000000000000000 8
b11101000000000000000000000000010000000000000000000 U
b100000000011011100000000000000000000 T
b111111000100000000000000000000 !
b111111000100000000000000000000 Y
b10000000000000000000000 <
b10000001 J
b10000000000000000000000 :
b0 =
b1 L
b111111110 K
b100000000000000000000000 @
1.
b10 G
b100000000000000000000000 7
b111111101 E
b111111110 F
b100000000000000000000000 >
b10000000100100000000000000000000000 X
b11000 Z
b10 V
b100000000000000000000000 W
b1111100 M
b1111101 N
b100000000000000000000000 B
b0 D
1'
b111110000000000000000000000000 &
b111110000000000000000000000000 *
b111110100000000000000000000000 %
b111110100000000000000000000000 )
#60000
0'
#65000
0+
b11 H
b101010000000000000000000 8
b111111110 I
b100000000000000000000000 ?
b110000000000000000000000 9
b10000000000000000000000 ;
b11000000100000000000000000000000 !
b11000000100000000000000000000000 Y
b110101010000000000000000000 T
b111111110100000000000000000000000010000000000000000000000 U
b1111111 J
b11000000000000000000000 =
b111111111 K
0.
b0 G
b111000000000000000000000 7
b111111110 E
b111111111 F
b111000000000000000000000 X
b11000 Z
b0 V
b111000000000000000000000 W
b1111101 M
b1111110 N
1'
b111110100000000000000000000000 &
b111110100000000000000000000000 *
b111111000000000000000000000000 %
b111111000000000000000000000000 )
#70000
0'
#75000
b111111111 I
b111111110 H
b110000000000000000000000 8
b111111111100000000000000000000000010000000000000000000000 U
b1111111100110000000000000000000000 T
b111111111000000000000000000000 !
b111111111000000000000000000000 Y
b10000010 J
b1010000000000000000000 =
b0 K
b11 G
b101010000000000000000000 7
b111111111 E
b0 F
b110101010000000000000000000 X
b11000 Z
b11 V
b101010000000000000000000 W
b1111110 M
b1111111 N
1'
b111111000000000000000000000000 &
b111111000000000000000000000000 *
b111111100000000000000000000000 %
b111111100000000000000000000000 )
#80000
0'
#85000
b111111111 H
b0 I
b1000001001010000000000000000000 !
b1000001001010000000000000000000 Y
b1111111110110000000000000000000000 T
b100000000000000000000000010000000000000000000000 U
b1111101 J
b10000000000000000000000 =
b11000000000000000000000 <
b101000000000000000000000 @
b111111110 G
b110000000000000000000000 7
b11000000000000000000000 :
b101000000000000000000000 >
b1111111100110000000000000000000000 X
b11000 Z
b111111110 V
b110000000000000000000000 W
b110000000000000000000000 A
b10000000000000000000000 C
b101000000000000000000000 B
b1000000000000000000000 D
1'
b111111010000000000000000000000 &
b111111010000000000000000000000 *
b111111101000000000000000000000 %
b111111101000000000000000000000 )
#90000
0'
#95000
b101000000000000000000000 ?
b1000000000000000000000000 9
b11000000000000000000000 ;
b0 H
b101000000000000000000000011000000000000000000000 U
b110000000000000000000000 T
b111110110000000000000000000000 !
b111110110000000000000000000000 Y
b110000000000000000000000 <
b1111110 J
0O
b110000000000000000000000 :
b0 L
b110000000000000000000000 @
b111111111 G
b0 E
b110000000000000000000000 >
b1111111110110000000000000000000000 X
b11000 Z
b111111111 V
b1111111 M
b110000000000000000000000 B
b10000000000000000000000 D
1'
b111111110000000000000000000000 &
b111111110000000000000000000000 *
b111111110000000000000000000000 %
b111111110000000000000000000000 )
#100000
0'
#105000
b1000000000000000000000000 8
b110000000000000000000000 ?
b1100000000000000000000000 9
b110000000000000000000000 ;
b111111010000000000000000000000 !
b111111010000000000000000000000 Y
b1000000000000000000000000 T
b110000000000000000000000110000000000000000000000 U
b1111111 J
b100000000000000000000000 @
b111000000000000000000000 <
b0 G
b100000000000000000000000 >
b111000000000000000000000 :
b110000000000000000000000 X
b11000 Z
b0 V
b100000000000000000000000 A
b0 C
b111000000000000000000000 B
b11000000000000000000000 D
1'
b111111100000000000000000000000 &
b111111100000000000000000000000 *
b111111111000000000000000000000 %
b111111111000000000000000000000 )
#110000
0'
#115000
b100000000000000000000000 ?
b1011000000000000000000000 9
b111000000000000000000000 ;
b1100000000000000000000000 8
b100000000000000000000000111000000000000000000000 U
b1100000000000000000000000 T
b111111110000000000000000000000 !
b111111110000000000000000000000 Y
11
b10000000 J
1O
b0 =
b111111110 K
b1 L
b110000000000000000000000 <
b1 G
b100000000000000000000000 7
14
b111111101 E
1-
b111111110 F
b10000000000000000000000 :
b10100000000000000000000000 X
b11000 Z
b1 V
b100000000000000000000000 W
15
b1111100 M
16
b1111101 N
b100000000000000000000000 B
b0 D
1'
b10111110000000000000000000000000 &
b10111110000000000000000000000000 *
b10111110100000000000000000000000 %
b10111110100000000000000000000000 )
#120000
0'
#125000
b1011000000000000000000000 8
13
1,
10
b111111110 I
b1010000000000000000000000 9
b110000000000000000000000 ;
b1000000000000000000000000000000 !
b1000000000000000000000000000000 Y
b1011000000000000000000000 T
b111111111110100000000000000000000000110000000000000000000000 U
b10000000000000000000000 =
b111111111 K
b110000000000000000000000 7
b111111110 E
b111111111 F
b10110000000000000000000000 X
b11000 Z
b1 V
b110000000000000000000000 W
b1111101 M
b1111110 N
1'
b10111110100000000000000000000000 &
b10111110100000000000000000000000 *
b10111111000000000000000000000000 %
b10111111000000000000000000000000 )
#130000
0'
#135000
b111111111 I
12
1+
1/
b111111110 H
b110000000000000000000000 8
b111111111111100000000000000000000000110000000000000000000000 U
b1111111111100110000000000000000000000 T
b1000000010000000000000000000000 !
b1000000010000000000000000000000 Y
b1100000000000000000000 =
b0 K
b101100000000000000000000 7
b111111111 E
b0 F
b10101100000000000000000000 X
b11000 Z
b1 V
b101100000000000000000000 W
b1111110 M
b1111111 N
1'
b10111111000000000000000000000000 &
b10111111000000000000000000000000 *
b10111111100000000000000000000000 %
b10111111100000000000000000000000 )
#140000
0'
#145000
b111111111 H
b0 I
b1000000001100000000000000000000 !
b1000000001100000000000000000000 Y
b1111111111110110000000000000000000000 T
b111000000000100000000000000000000000110000000000000000000000 U
b1111101 J
b101000000000000000000000 <
b11000000000000000000000 @
b10000000000000000000000 =
1.
b111111110 G
b110000000000000000000000 7
b11000000000000000000000 :
b101000000000000000000000 >
b11111111100110000000000000000000000 X
b11000 Z
b111111110 V
b110000000000000000000000 W
b110000000000000000000000 A
b10000000000000000000000 C
b101000000000000000000000 B
b1000000000000000000000 D
1'
b10111111010000000000000000000000 &
b10111111010000000000000000000000 *
b10111111101000000000000000000000 %
b10111111101000000000000000000000 )
#150000
0'
#155000
b11000000000000000000000 ?
b1000000000000000000000000 9
b101000000000000000000000 ;
b0 H
b111000000000011000000000000000000000101000000000000000000000 U
b1110000000000110000000000000000000000 T
b10111110110000000000000000000000 !
b10111110110000000000000000000000 Y
b10000000000000000000000 <
b1111110 J
0O
b110000000000000000000000 :
b10000000000000000000000 @
b0 L
b111111111 G
b0 E
b110000000000000000000000 >
b11111111110110000000000000000000000 X
b11000 Z
b111111111 V
b1111111 M
b110000000000000000000000 B
b10000000000000000000000 D
1'
b10111111110000000000000000000000 &
b10111111110000000000000000000000 *
b10111111110000000000000000000000 %
b10111111110000000000000000000000 )
#160000
0'
#165000
b1000000000000000000000000 8
b10000000000000000000000 ?
b100000000000000000000000 9
b10000000000000000000000 ;
b10111111010000000000000000000000 !
b10111111010000000000000000000000 Y
b1110000000001000000000000000000000000 T
b111000000000010000000000000000000000010000000000000000000000 U
b1111111 J
b100000000000000000000000 @
b1000000000000000000000 <
b0 G
b100000000000000000000000 >
b111000000000000000000000 :
b10000000000110000000000000000000000 X
b11000 Z
b0 V
b100000000000000000000000 A
b0 C
b111000000000000000000000 B
b11000000000000000000000 D
1'
b10111111100000000000000000000000 &
b10111111100000000000000000000000 *
b10111111111000000000000000000000 %
b10111111111000000000000000000000 )
#170000
0'
#175000
b100000000000000000000000 ?
b101000000000000000000000 9
b1000000000000000000000 ;
b1100000000000000000000000 8
b111000000000100000000000000000000000001000000000000000000000 U
b1110000000001100000000000000000000000 T
b10111111110000000000000000000000 !
b10111111110000000000000000000000 Y
01
04
b10000000 J
1O
b0 =
b1 K
b111000000000000000000000 <
b10 L
b1 G
b100000000000000000000000 7
b111111111 E
1-
b1 F
b1000000000000000000000 :
b10000000010100000000000000000000000 X
b11000 Z
b1 V
b100000000000000000000000 W
b1111110 M
06
b10000000 N
b100000000000000000000000 B
b0 D
1'
b10111111000000000000000000000000 &
b10111111000000000000000000000000 *
b1000000000000000000000000000000 %
b1000000000000000000000000000000 )
#180000
0'
#185000
b1011000000000000000000000 8
03
00
b1 I
b1011000000000000000000000 9
b111000000000000000000000 ;
b11000000000000000000000000000000 !
b11000000000000000000000000000000 Y
b1110000000001011000000000000000000000 T
b10000000001100000000000000000000000111000000000000000000000 U
b110000000000000000000000 <
b10000000000000000000000 :
b10000000000000000000000 =
b1 L
b110000000000000000000000 @
b110000000000000000000000 7
b0 E
b110000000000000000000000 >
b10000000010110000000000000000000000 X
b11000 Z
b1 V
b110000000000000000000000 W
b1111111 M
b110000000000000000000000 B
b10000000000000000000000 D
1'
b10111111100000000000000000000000 &
b10111111100000000000000000000000 *
b1000000010000000000000000000000 %
b1000000010000000000000000000000 )
#190000
0'
#195000
b110000000000000000000000 ?
b1100000000000000000000000 9
b110000000000000000000000 ;
02
0/
b1 H
b10000000001110000000000000000000000110000000000000000000000 U
b100000000011011000000000000000000000 T
b11000000010000000000000000000000 !
b11000000010000000000000000000000 Y
b1100000000000000000000 =
b10 K
b101000000000000000000000 @
b101100000000000000000000 7
b1 E
b10 F
b101000000000000000000000 >
b10000000010101100000000000000000000 X
b11000 Z
b1 V
b101100000000000000000000 W
b10000000 M
b10000001 N
b101000000000000000000000 B
b1000000000000000000000 D
1'
b11000000000000000000000000000000 &
b11000000000000000000000000000000 *
b1000000101000000000000000000000 %
b1000000101000000000000000000000 )
#200000
0'
#205000
b1100000000000000000000000 8
b10 I
b1011000000000000000000000 9
b101000000000000000000000 ?
b11000000001100000000000000000000 !
b11000000001100000000000000000000 Y
b100000000011100000000000000000000000 T
b10000000010101000000000000000000000110000000000000000000000 U
14
0-
b1111111 J
0O
b110000000000000000000000 :
b10000000000000000000000 =
b0 L
b100000000000000000000000 @
0.
b0 G
b110000000000000000000000 7
b10 E
b100000000000000000000000 >
b110000000000000000000000 X
b0 V
b11000 Z
b110000000000000000000000 W
b10000001 M
b110000000000000000000000 B
b10000000000000000000000 D
1'
b11000000100000000000000000000000 &
b11000000100000000000000000000000 *
b1000000110000000000000000000000 %
b1000000110000000000000000000000 )
#210000
0'
#215000
13
0,
b1010000000000000000000000 9
b100000000000000000000000 ?
b10 H
b1011000000000000000000000 8
b100000000010100000000000000000000000110000000000000000000000 U
b100000000101011000000000000000000000 T
b111111110000000000000000000000 !
b111111110000000000000000000000 Y
01
b11 K
04
1-
b10000000 J
b101000000000000000000000 @
1O
b0 =
b1 L
b101100000000000000000000 <
b1 G
b1100000000000000000000000 7
b101000000000000000000000 >
b11 F
b10100000000000000000000 :
b11100000000000000000000000 X
b11000 Z
b1 V
b1100000000000000000000000 W
b101000000000000000000000 A
b1000000000000000000000 C
b10000010 N
b101000000000000000000000 B
b1000000000000000000000 D
1'
b11000000101000000000000000000000 &
b11000000101000000000000000000000 *
b1000001001000000000000000000000 %
b1000001001000000000000000000000 )
#220000
0'
#225000
12
0+
b1010000000000000000000000 8
03
1,
b11 I
b101000000000000000000000 ?
b1010100000000000000000000 9
b101100000000000000000000 ;
b1000000000000000000000000000000 !
b1000000000000000000000000000000 Y
b1000000000101010000000000000000000000 T
b10000000011101000000000000000000000101100000000000000000000 U
01
0O
b101000000000000000000000 :
b10000000000000000000000 =
b11000000000000000000000 <
b101000000000000000000000 @
b0 L
b10 K
b110000000000000000000000 7
1-
04
b10 F
b10110000000000000000000000 X
b11000 Z
b1 V
b110000000000000000000000 W
05
16
b10000001 N
1'
b1000000101000000000000000000000 &
b1000000101000000000000000000000 *
b11000000101000000000000000000000 %
b11000000101000000000000000000000 )
#230000
0'
#235000
b10 I
b1000000000000000000000000 9
b11000000000000000000000 ;
02
1+
b11 H
b1010100000000000000000000 8
b10000000010101000000000000000000000011000000000000000000000 U
b100000000111010100000000000000000000 T
b1000000010000000000000000000000 !
b1000000010000000000000000000000 Y
b100000000000000000000000 <
b0 =
b11 K
b100000000000000000000000 @
b100000000000000000000000 7
b11 E
b100000000000000000000000 >
b11 F
b100000000000000000000000 :
b10100000000000000000000000 X
b11000 Z
b1 V
b100000000000000000000000 W
b10000010 M
b100000000000000000000000 A
b0 C
b10000010 N
b100000000000000000000000 B
b0 D
1'
b1000001000000000000000000000000 &
b1000001000000000000000000000000 *
b11000001000000000000000000000000 %
b11000001000000000000000000000000 )
#240000
0'
