RTL/TRNG/Von_Neumann_Corrector.v
/*
module Von_Neumann_Corrector(
	input clk,
	input reset_n,
	input enable,
	input raw_bit,
	output reg valid,
	output reg processed_bit
);

localparam S0 = 2'b00;
localparam S1 = 2'b01; 
localparam S2 = 2'b10;

reg [1:0] curr_state, next_state;
always@(posedge clk or negedge reset_n) begin
	if(!reset_n) begin
		curr_state <= S0;
	end else if(enable) begin
		curr_state <= next_state;	
	end
end

always@(*) begin
	next_state <= curr_state;
	valid <= 0;
	processed_bit <= 0;
	case(curr_state)
		S0: begin
			next_state <= raw_bit ? S1 : S2;
			valid <= 0;
		end

		S1: begin
			next_state <= S0;
			if(!raw_bit) begin
				valid <= 1;
				processed_bit <= 1;
			end 
		end

		S2: begin
			next_state <= S0;
			if(raw_bit) begin
				valid <= 1;
				processed_bit <= 0;
			end
		end

		default: begin
			valid <= 0;
			processed_bit <=0;
			next_state <= curr_state;
		end

	endcase
end

endmodule
*/
module Von_Neumann_Corrector(
    input  wire clk,
    input  wire reset_n,
    input  wire enable,        // Tín hiệu báo raw_bit hợp lệ
    input  wire raw_bit,
    output reg  valid,         // Báo hiệu đã thu được bit ngẫu nhiên chuẩn
    output reg  processed_bit  // Bit ngẫu nhiên đã khử bias
);

    // Định nghĩa trạng thái
    localparam S_WAIT_FIRST = 1'b0;
    localparam S_WAIT_SECOND = 1'b1;

    reg current_state, next_state;
    reg first_bit_captured; // Lưu giá trị bit đầu tiên

    // --- 1. Sequential Logic (Flip-Flops) ---
    // Cập nhật trạng thái và lưu bit đầu tiên
    always @(posedge clk or negedge reset_n) begin
        if (!reset_n) begin
            current_state <= S_WAIT_FIRST;
            first_bit_captured <= 1'b0;
        end else if (enable) begin
            current_state <= next_state;
            // Nếu đang ở trạng thái đợi bit đầu, lưu raw_bit lại
            if (current_state == S_WAIT_FIRST) begin
                first_bit_captured <= raw_bit;
            end
        end
    end

    // --- 2. Combinational Logic (Next State & Output) ---
    always @(*) begin
        // Giá trị mặc định để tránh Latch
        next_state    = current_state;
        valid         = 1'b0;
        processed_bit = 1'b0;

        case (current_state)
            S_WAIT_FIRST: begin
                // Luôn chuyển sang trạng thái đợi bit thứ 2
                // (Việc lưu bit diễn ra ở block Sequential bên trên)
                next_state = S_WAIT_SECOND;
            end

            S_WAIT_SECOND: begin
                next_state = S_WAIT_FIRST; // Luôn quay về đợi cặp mới
                
                // So sánh bit cũ (first_bit_captured) và bit mới (raw_bit)
                if (first_bit_captured != raw_bit) begin
                    // Nếu 2 bit khác nhau -> Valid
                    valid = 1'b1;
                    
                    // Von Neumann logic:
                    // Cặp "10" -> Output 1 (Lấy bit đầu)
                    // Cặp "01" -> Output 0 (Lấy bit đầu)
                    // => processed_bit chính là first_bit_captured
                    processed_bit = first_bit_captured; 
                end
                // Nếu giống nhau (00 hoặc 11) -> valid vẫn là 0 -> Bỏ qua
            end
        endcase
    end

endmodule

testbench/Von_Neumann_Corrector_tb.v
`timescale 1ns/1ps

module von_neumann_tb;

    reg clk;
    reg reset_n;
    reg enable;
    reg raw_bit;

    wire valid;
    wire processed_bit;

    // DUT
    Von_Neumann_Corrector dut (
        .clk(clk),
        .reset_n(reset_n),
        .enable(enable),
        .raw_bit(raw_bit),
        .valid(valid),
        .processed_bit(processed_bit)
    );

    // Clock 10ns period
    always #5 clk = ~clk;

    // Raw bitstream from the figure
    reg [11:0] raw_stream = 12'b100011010010;
    integer i;

    initial begin
        // VCD dump
        $dumpfile("von_neumann_tb.vcd");
        $dumpvars(0, von_neumann_tb);

        clk = 0;
        reset_n = 0;
        enable = 0;
        raw_bit = 0;

        // Reset
        #20;
        reset_n <= 1;

        // Feed raw bits MSB → LSB
        for (i = 11; i >= 0; i = i - 1) begin
        	enable  <= 1;
            	raw_bit <= raw_stream[i];
            	@(posedge clk);
        end
	enable <= 0;

        // Let FSM finish
        repeat(4) @(posedge clk);

        $finish;
    end

    // Monitor output
    always @(posedge clk) begin
        if (valid)
            $display("Time %0t : valid=%b processed_bit=%b", $time,valid, processed_bit);
    end

endmodule

RTL/TRNG/von_neumann_tb.vcd
$date
	Tue Jan 20 20:26:20 2026
$end
$version
	Icarus Verilog
$end
$timescale
	1ps
$end
$scope module von_neumann_tb $end
$var wire 1 ! valid $end
$var wire 1 " processed_bit $end
$var reg 1 # clk $end
$var reg 1 $ enable $end
$var reg 1 % raw_bit $end
$var reg 12 & raw_stream [11:0] $end
$var reg 1 ' reset_n $end
$var integer 32 ( i [31:0] $end
$scope module dut $end
$var wire 1 # clk $end
$var wire 1 $ enable $end
$var wire 1 % raw_bit $end
$var wire 1 ' reset_n $end
$var parameter 1 ) S_WAIT_FIRST $end
$var parameter 1 * S_WAIT_SECOND $end
$var reg 1 + current_state $end
$var reg 1 , first_bit_captured $end
$var reg 1 - next_state $end
$var reg 1 " processed_bit $end
$var reg 1 ! valid $end
$upscope $end
$upscope $end
$enddefinitions $end
$comment Show the parameter values. $end
$dumpall
1*
0)
$end
#0
$dumpvars
1-
0,
0+
bx (
0'
b100011010010 &
0%
0$
0#
0"
0!
$end
#5000
1#
#10000
0#
#15000
1#
#20000
1-
1%
1$
1'
0#
b1011 (
#25000
1"
1!
0-
1,
1+
0%
b1010 (
1#
#30000
0#
#35000
1-
0"
0!
0+
b1001 (
1#
#40000
0#
#45000
0-
0,
1+
b1000 (
1#
#50000
0#
#55000
1-
0+
1%
b111 (
1#
#60000
0#
#65000
0-
1,
1+
b110 (
1#
#70000
0#
#75000
1-
0+
0%
b101 (
1#
#80000
0#
#85000
1!
0-
0,
1+
1%
b100 (
1#
#90000
0#
#95000
1-
0!
0+
0%
b11 (
1#
#100000
0#
#105000
0-
1+
b10 (
1#
#110000
0#
#115000
1-
0+
1%
b1 (
1#
#120000
0#
#125000
1"
1!
0-
1,
1+
0%
b0 (
1#
#130000
0#
#135000
1-
0"
0!
0+
0$
b11111111111111111111111111111111 (
1#
